formsite_util/__init__.py
formsite_util/_cache.py
formsite_util/_download.py
formsite_util/_download_async.py
formsite_util/_form.py
formsite_util/_form_data.py
formsite_util/_form_fetcher.py
formsite_util/_form_parser.py
formsite_util/_list.py
formsite_util/_logger.py
formsite_util/_parameters.py
formsite_util/cli.py
formsite_util/consts.py
formsite_util/error.py
formsite_util/internal.py
formsite_util/legacy/__init__.py
formsite_util/legacy/api.py
formsite_util/legacy/auth.py
formsite_util/legacy/downloader.py
formsite_util/legacy/interfaces.py
formsite_util/legacy/processing.py
formsite_util-2.1.1.dist-info/entry_points.txt
formsite_util-2.1.1.dist-info/LICENSE.md
formsite_util-2.1.1.dist-info/WHEEL
formsite_util-2.1.1.dist-info/METADATA
formsite_util-2.1.1.dist-info/RECORD
