Metadata-Version: 2.1
Name: formsite-util
Version: 2.1.1
Summary: Python library and CLI tool for interacing with the FormSite API
Home-page: https://github.com/strny0/formsite-utility/
License: MIT
Keywords: formsite,form,api,download,export
Author: Jakub Strnad
Author-email: jakub.strnad@protonmail.com
Requires-Python: >=3.8,<4.0
Classifier: Environment :: Console
Classifier: License :: OSI Approved :: MIT License
Classifier: Operating System :: OS Independent
Classifier: Programming Language :: Python :: 3
Classifier: Programming Language :: Python :: 3.10
Classifier: Programming Language :: Python :: 3.8
Classifier: Programming Language :: Python :: 3.9
Classifier: Topic :: Software Development :: Libraries :: Python Modules
Classifier: Topic :: Utilities
Classifier: Typing :: Typed
Provides-Extra: serialization
Requires-Dist: aiohttp (>=3.8.1,<4.0.0)
Requires-Dist: colorama (>=0.4,<0.5)
Requires-Dist: pandas (>=1.4.0,<2.0.0)
Requires-Dist: pytz (>=2021.0,<2022.0)
Requires-Dist: requests (>=2.0.0,<3.0.0)
Requires-Dist: tqdm (>=4.60,<5.0)
Project-URL: Bug Tracker, https://github.com/strny0/formsite-utility/issues
Project-URL: Repository, https://github.com/strny0/formsite-utility/
